{"data":[{"id":"278120302242816","from":{"name":"Novak Garden Design & Construction, LLC","category":"Local business","id":"161987050522809"},"picture":"http:\/\/photos-g.ak.fbcdn.net\/hphotos-ak-snc7\/381718_278120302242816_161987050522809_706854_160858264_s.jpg","source":"http:\/\/sphotos.xx.fbcdn.net\/hphotos-snc7\/s720x720\/381718_278120302242816_161987050522809_706854_160858264_n.jpg","height":540,"width":720,"images":[{"width":720,"height":540,"source":"http:\/\/sphotos.xx.fbcdn.net\/hphotos-snc7\/s720x720\/381718_278120302242816_161987050522809_706854_160858264_n.jpg"},{"width":180,"height":135,"source":"http:\/\/photos-g.ak.fbcdn.net\/hphotos-ak-snc7\/381718_278120302242816_161987050522809_706854_160858264_a.jpg"},{"width":130,"height":97,"source":"http:\/\/photos-g.ak.fbcdn.net\/hphotos-ak-snc7\/381718_278120302242816_161987050522809_706854_160858264_s.jpg"},{"width":75,"height":56,"source":"http:\/\/photos-g.ak.fbcdn.net\/hphotos-ak-snc7\/381718_278120302242816_161987050522809_706854_160858264_t.jpg"}],"link":"http:\/\/www.facebook.com\/photo.php?fbid=278120302242816&set=a.278120265576153.64963.161987050522809&type=1","icon":"http:\/\/static.ak.fbcdn.net\/rsrc.php\/v1\/yz\/r\/StEh3RhPvjk.gif","created_time":"2012-01-16T01:57:38+0000","position":1,"updated_time":"2012-01-16T01:57:39+0000","comments":{"data":[{"id":"278120302242816_601361","from":{"name":"Meghan Harris","id":"531321785"},"message":"I wanna grow this flower in my yard is it hard to grow ","created_time":"2012-01-16T02:10:20+0000"},{"id":"278120302242816_601365","from":{"name":"Novak Garden Design & Construction, LLC","category":"Local business","id":"161987050522809"},"message":"Not at all!  Let me know come spring, and i will give you a piece, you can just plant and enjoy!","created_time":"2012-01-16T02:19:17+0000"},{"id":"278120302242816_601805","from":{"name":"Meghan Harris","id":"531321785"},"message":"Ok thanks :)","created_time":"2012-01-16T12:06:54+0000"}],"paging":{"next":"https:\/\/graph.facebook.com\/278120302242816\/comments?limit=25&offset=25&__after_id=278120302242816_601805"}},"likes":{"data":[{"id":"531321785","name":"Meghan Harris"}],"paging":{"next":"https:\/\/graph.facebook.com\/278120302242816\/likes?limit=25&offset=25&__after_id=531321785"}}},{"id":"278120328909480","from":{"name":"Novak Garden Design & Construction, LLC","category":"Local business","id":"161987050522809"},"picture":"http:\/\/photos-a.ak.fbcdn.net\/hphotos-ak-ash4\/401560_278120328909480_161987050522809_706855_1398308955_s.jpg","source":"http:\/\/sphotos.xx.fbcdn.net\/hphotos-ash4\/s720x720\/401560_278120328909480_161987050522809_706855_1398308955_n.jpg","height":540,"width":720,"images":[{"width":720,"height":540,"source":"http:\/\/sphotos.xx.fbcdn.net\/hphotos-ash4\/s720x720\/401560_278120328909480_161987050522809_706855_1398308955_n.jpg"},{"width":180,"height":135,"source":"http:\/\/photos-a.ak.fbcdn.net\/hphotos-ak-ash4\/401560_278120328909480_161987050522809_706855_1398308955_a.jpg"},{"width":130,"height":97,"source":"http:\/\/photos-a.ak.fbcdn.net\/hphotos-ak-ash4\/401560_278120328909480_161987050522809_706855_1398308955_s.jpg"},{"width":75,"height":56,"source":"http:\/\/photos-a.ak.fbcdn.net\/hphotos-ak-ash4\/401560_278120328909480_161987050522809_706855_1398308955_t.jpg"}],"link":"http:\/\/www.facebook.com\/photo.php?fbid=278120328909480&set=a.278120265576153.64963.161987050522809&type=1","icon":"http:\/\/static.ak.fbcdn.net\/rsrc.php\/v1\/yz\/r\/StEh3RhPvjk.gif","created_time":"2012-01-16T01:57:41+0000","position":2,"updated_time":"2012-01-16T01:57:42+0000"}],"paging":{"next":"https:\/\/graph.facebook.com\/278120265576153\/photos?limit=25&offset=25&__after_id=278120328909480"}}